{"type":"Design","zone":null,"children":[{"type":"Page","properties":{"id":"page1"},"children":[{"type":"Content","zone":"content","children":[{"type":"Collapsible","properties":{"heading":"Víctimas"},"children":[{"type":"Collapsible","properties":{"heading":"Víctima 1"},"children":[{"type":"Grid","properties":{"columns":3},"children":[{"type":"Block","children":[{"type":"Text","properties":{"text":"Documento de Identidad"}}]},{"type":"Block","properties":{"subtype":"b"},"children":[{"type":"SelectMenu","properties":{"options":{"type":"record-array","sortable":true,"recordType":{"text":"string","value":"string"},"children":[{"text":"Cédula de Ciudadania","value":"Value"},{"text":"Tarjeta de Identidad","value":"Value"},{"text":"...","value":"Value"}]}}}]},{"type":"Block","properties":{"subtype":"c"},"children":[{"type":"TextInput","properties":{"value":"Número","id":"text1"}}]}]},{"type":"Grid","children":[{"type":"Block","children":[{"type":"TextInput","properties":{"label":"Nombres","id":"text2"}}]},{"type":"Block","properties":{"subtype":"b"},"children":[{"type":"TextInput","properties":{"label":"Apellidos","id":"text3"}}]}]},{"type":"Grid","properties":{"columns":4},"children":[{"type":"Block","children":[{"type":"Text","properties":{"text":"Fecha Nacimiento y Sexo"}}]},{"type":"Block","properties":{"subtype":"b"},"children":[{"type":"TextInput","properties":{"id":"text4","label":" "}}]},{"type":"Block","properties":{"subtype":"c"},"children":[{"type":"SelectMenu","properties":{"options":{"type":"record-array","sortable":true,"recordType":{"text":"string","value":"string"},"children":[{"text":"Sin Información","value":"Value"},{"text":"Masculino","value":"Value"},{"text":"Femenino","value":"Value"}]}}}]},{"type":"Block","properties":{"subtype":"d"},"children":[{"type":"TextInput","properties":{"label":"Edad","id":"text5"}}]}]},{"type":"Grid","children":[{"type":"Block","children":[{"type":"Text","properties":{"text":"Nacionalidad"}}]},{"type":"Block","properties":{"subtype":"b"},"children":[{"type":"SelectMenu","properties":{"options":{"type":"record-array","sortable":true,"recordType":{"text":"string","value":"string"},"children":[{"text":"Sin Información","value":"Value"},{"text":"Venezolano","value":"Value"},{"text":"Colombiano","value":"Value"},{"text":"...","value":"Value"}]}}}]}]},{"type":"Grid","children":[{"type":"Block","children":[{"type":"Text","properties":{"text":"Etnia"}}]},{"type":"Block","properties":{"subtype":"b"},"children":[{"type":"SelectMenu","properties":{"options":{"type":"record-array","sortable":true,"recordType":{"text":"string","value":"string"},"children":[{"text":"Sin Información","value":"Value"},{"text":"Mestizo","value":"Value"},{"text":"Afro","value":"Value"},{"text":"...","value":"Value"}]}}}]}]},{"type":"Grid","children":[{"type":"Block","children":[{"type":"Text","properties":{"text":"Religion, Iglesia"}}]},{"type":"Block","properties":{"subtype":"b"},"children":[{"type":"SelectMenu","properties":{"options":{"type":"record-array","sortable":true,"recordType":{"text":"string","value":"string"},"children":[{"text":"Sin Información","value":"Value"},{"text":"Católico","value":"Value"},{"text":"Evangélico","value":"Value"},{"text":"...","value":"Value"}]}}}]}]},{"type":"Grid","children":[{"type":"Block","children":[{"type":"Text","properties":{"text":"Orientación Sexual"}}]},{"type":"Block","properties":{"subtype":"b"},"children":[{"type":"SelectMenu","properties":{"options":{"type":"record-array","sortable":true,"recordType":{"text":"string","value":"string"},"children":[{"text":"Heterosexual","value":"Value"},{"text":"Lesbiana","value":"Value"},{"text":"Gay","value":"Value"},{"text":"...","value":"Value"}]}}}]}]},{"type":"Grid","children":[{"type":"Block","children":[{"type":"Text","properties":{"text":"Idiomas"}}]},{"type":"Block","properties":{"subtype":"b"},"children":[{"type":"SelectMenu","properties":{"options":{"type":"record-array","sortable":true,"recordType":{"text":"string","value":"string"},"children":[{"text":"Sin Información","value":"Value"},{"text":"Mestizo","value":"Value"},{"text":"Afro","value":"Value"},{"text":"...","value":"Value"}]}}}]}]},{"type":"Grid","children":[{"type":"Block","children":[{"type":"Text","properties":{"text":"Lugar Nacimiento"}}]},{"type":"Block","properties":{"subtype":"b"},"children":[{"type":"SelectMenu","properties":{"options":{"type":"record-array","sortable":true,"recordType":{"text":"string","value":"string"},"children":[{"text":"País","value":"Value"},{"text":"Mestizo","value":"Value"},{"text":"Afro","value":"Value"},{"text":"...","value":"Value"}]}}},{"type":"SelectMenu","properties":{"options":{"type":"record-array","sortable":true,"recordType":{"text":"string","value":"string"},"children":[{"text":"Corr/Prov/Estado","value":"Value"},{"text":"Mestizo","value":"Value"},{"text":"Afro","value":"Value"},{"text":"...","value":"Value"}]}}},{"type":"SelectMenu","properties":{"options":{"type":"record-array","sortable":true,"recordType":{"text":"string","value":"string"},"children":[{"text":"Municipio","value":"Value"},{"text":"Mestizo","value":"Value"},{"text":"Afro","value":"Value"},{"text":"...","value":"Value"}]}}},{"type":"SelectMenu","properties":{"options":{"type":"record-array","sortable":true,"recordType":{"text":"string","value":"string"},"children":[{"text":"Ciudad","value":"Value"},{"text":"San Cristobal","value":"Value"},{"text":"Nule","value":"Value"},{"text":"...","value":"Value"}]}}},{"type":"TextInput","properties":{"label":"Vereda/Parroquia","id":"text6"}}]}]},{"type":"Grid","children":[{"type":"Block","children":[{"type":"Text","properties":{"text":"Lugar Residencia"}}]},{"type":"Block","properties":{"subtype":"b"},"children":[{"type":"SelectMenu","properties":{"options":{"type":"record-array","sortable":true,"recordType":{"text":"string","value":"string"},"children":[{"text":"Sin Información","value":"Value"},{"text":"País/Depto/Mcpo/Ciudad","value":"Value"},{"text":"VENEZUELA","value":"Value"},{"text":"...","value":"Value"}]}}}]}]},{"type":"Grid","children":[{"type":"Block","children":[{"type":"Text","properties":{"text":"Estado Civil"}}]},{"type":"Block","properties":{"subtype":"b"},"children":[{"type":"SelectMenu","properties":{"options":{"type":"record-array","sortable":true,"recordType":{"text":"string","value":"string"},"children":[{"text":"SIN INFORMACIÓN","value":"Value"},{"text":"CASADO(A)","value":"Value"},{"text":"SOLTERO(A)","value":"Value"},{"text":"...","value":"Value"}]}}}]}]},{"type":"Grid","children":[{"type":"Block","children":[{"type":"Text","properties":{"text":"Nivel Escolaridad"}}]},{"type":"Block","properties":{"subtype":"b"},"children":[{"type":"SelectMenu","properties":{"options":{"type":"record-array","sortable":true,"recordType":{"text":"string","value":"string"},"children":[{"text":"SIN INFORMACIÓN","value":"Value"},{"text":"PREESCOLAR","value":"Value"},{"text":"PRIMARIA","value":"Value"},{"text":"...","value":"Value"}]}}}]}]},{"type":"Grid","children":[{"type":"Block","children":[{"type":"Text","properties":{"text":"Profesión"}}]},{"type":"Block","properties":{"subtype":"b"},"children":[{"type":"SelectMenu","properties":{"options":{"type":"record-array","sortable":true,"recordType":{"text":"string","value":"string"},"children":[{"text":"Sin Información","value":"Value"},{"text":"ABOGADO","value":"Value"},{"text":"ADMINISTRADOR PÚBLICO","value":"Value"},{"text":"...","value":"Value"}]}}}]}]},{"type":"Button","properties":{"text":"Eliminar Víctima"}}]},{"type":"Collapsible","properties":{"heading":"Víctima 2"}},{"type":"Button","properties":{"text":"Añadir Víctima","id":"button1"}}]}]}]}],"pInfo":{"name":"SIVeL2SJRV-CASO-02-INDIVIDUALES","theme":"Default","accessDate":1385734309688,"device":{"name":"Phones","screenWidth":320,"screenHeight":480,"rotating":false}}}
